llm/__init__.py
llm/chatllm.py
llm/qa.py
llm/utils.py
llm/applications/ChatPDF.py
llm/applications/Question2Answer.py
llm/applications/__init__.py
llm/applications/pipeline.py
llm/clis/README.md
llm/clis/__init__.py
llm/clis/cli.py
llm/docutils/__init__.py
llm/docutils/doc_embedding.py
llm/docutils/doc_parse.py
llm/kb/FaissANN.py
llm/kb/__init__.py
llm/kb/kbqa.py
llm/knowledge_base/__init__.py
llm/knowledge_base/lite.py
llm/uis/__init__.py
llm4gpt-2023.4.21.19.25.3.dist-info/AUTHORS.rst
llm4gpt-2023.4.21.19.25.3.dist-info/LICENSE
llm4gpt-2023.4.21.19.25.3.dist-info/METADATA
llm4gpt-2023.4.21.19.25.3.dist-info/WHEEL
llm4gpt-2023.4.21.19.25.3.dist-info/entry_points.txt
llm4gpt-2023.4.21.19.25.3.dist-info/top_level.txt
llm4gpt-2023.4.21.19.25.3.dist-info/RECORD
